{
  "doc_id": "doc_f16372d09155",
  "title": "Habitto-Mobile-Docs.pdf",
  "content": "Habitto Mobile – Product & Engineering\nPurpose\nEnd-to-end documentation for product flows, architecture, and QA across Authentication, Onboarding, Chat,\nSession Booking, Support, Referral, Money Transfer, Investment, Insurance, and Money Habits (Manabu).\nTable of Contents\nAuthentication\nOnboarding\nChat (Twilio)\nSession Booking\nSupport\nReferral\nMoney Transfer\nInvestment\nInsurance\nMoney Habits (Manabu)\nApp Architecture\nAnalytics & Events\nPermissions & Privacy\nNotifications & Deep Links\nRelease Process & QA\nConventions\nFile paths in backticks (e.g., src/screens/...)\nEvents snake_case by domain (e.g., auth_biometric_success)\nUse InteractionManager.runAfterInteractions to defer heavy work\nAuthentication\nOverview\nSecure access; foreground lock; biometrics; lifecycle management.\nArchitecture\nHooks: src/screens/Auth/AppLock/useForegroundApplockHook.tsx\nBiometrics UI: src/screens/Common/Biometrics.tsx\nActions: common/actions/appLock.actions.ts, common/actions/common.actions.ts,\ncommon/actions/auth.actions.ts\nReducers: common/reducers/appState.reducer.ts, common/reducers/auth.reducer.ts\nSelectors: common/selectors/appLockSelector.selector.tsx,\ncommon/selectors/authSelectors.selector.tsx\nUtilities: common/lib/DateHandler.ts, common/lib/utils.ts (delay, runInBackground)\nScreens\nBiometric prompt (native) and App Lock gate\nError states: unavailable sensor, opt-out\nFlows\nFirst-time biometric:\nDetect device → prompt → store preference → continue.\nResume from background:\nIf lastActive ≥ 1h and user authenticated: lock → biometric prompt → resume.\nElse: resume silently and run updates (ACTIONS.CHECK_UPDATES_N_RESUME_APP).\nFallback: if biometric disabled/unavailable → passcode or bypass per policy.\nLifecycle & State\nForeground hook:\nOn Active: setFromBackground(true) → setForegroundCheckStatus(true) →\nbiometric if needed → setForegroundCheckStatus(false) → resume tasks.\nOn Background: SET_LAST_ACTIVE_TIME_STAMP, setFromBackground(false).\nEdge Cases\nNotification deep-link while locked → defer until unlocked.\nRapid background/foreground flaps → deduplicate prompts.\nANR mitigation: defer heavy work using InteractionManager.\nAnalytics\nauth_biometric_prompt_shown, auth_biometric_success, auth_biometric_failure, auth_lock_shown,\nauth_resume_completed\nQA\nDevices with FaceID/TouchID/None\nResume at <1h and ≥1h\nDeep-links while locked\nAirplane-mode resume\nOnboarding\nOverview\nPermissions, KYC/GMO consent, initial feature gating, tooltips.\nArchitecture\nScreen: src/screens/Dashboard/Home/Home.screen.tsx\nActions: support.actions.ts (e.g., getAccountOpeningStatus,\ngetGMOconsentAgreement), common.actions.ts\nSelectors: accountOpeningStatusSelector, localeSelector\nModals: components/PermissionRequestModal.component.tsx\nDeep-links: root handlers in AppNavigation.tsx\nSteps\nPermissions: notifications (and iOS ATT)\nAccount opening:\nFORM_NOT_SUBMITTED → start application\nPROBLEM_IN_DATA → re-apply\nWITHDRAWN/REJECTED → alternate CTAs\nACCOUNT_ACTIVATED & funded → dashboard\nConsent: open URL, return via deep link.\nInitial setting card if activated but not funded.\nTooltips sequence (savings → insurance → investment → more).\nDeep Links\nWeekly yield modal\nConsent refresh link (refresh helpers → clear deep link)\nEdge Cases\nForeground checks can block initial deep-link handling; defer.\nAvoid duplicate API races; debounce where needed.\nAnalytics\nonboarding_permission_prompt_shown/accepted\nonboarding_kyc_status_updated\nonboarding_initial_setting_action\nQA\niOS/Android first-run permutations\nKYC return flows\nPermission toggles mid-flow\nChat (Twilio)\nOverview\nReal-time messaging with text/media; typing; read index; push deep-links.\nArchitecture\nEvents: src/navigation/AppRoutes.tsx (listeners, deferrals)\nUI: react-native-chat-ui/src/components/*\nState: messages, typing, last read index\nModels\nMessage: sid, author, body, timestamp, type (text/image/video/audio/file), attributes, status\n(sending/sent/failed)\nTyping: author → boolean\nRead index: per thread\nEvents\nonMessagesLoad(messages):\nDefer heavy init; set message list; set read index\nmessageAdded(message):\nToggle typing false; increment read index; for media, resolve temp URLs; dispatch updates\nmessageUpdated/Removed:\nUpdate local store accordingly\nInput (Android specifics)\nHeight 40–100 using onContentSizeChange\ntextAlignVertical: 'top'; scrollEnabled when keyboard visible\nHide attachment/AI row when keyboard visible; animate height/opacity\nWhen keyboard hidden, show truncated overlay (ellipsizeMode=\"head\") with the inputʼs text hidden\n(transparent color) to avoid value mutation issues.\nPerformance\nInteractionManager.runAfterInteractions for heavy events\nDebounced dispatches; clean up listeners\nLazy load with React.Suspense and fallback\nAnalytics\nchat_thread_opened/closed\nchat_message_sent/received\nchat_media_sent_{type}\nchat_typing_started/stopped\nchat_push_deeplink_opened\nQA\nHigh-volume inbound messages\nAll attachment types\nPush deep-link → thread while app locked/unlocked\nAndroid keyboard: growth/shrink and accessory row behavior\nSession Booking\nOverview\nBook/reschedule advisor sessions; history with status tabs.\nArchitecture\nPicker: CreateSession/SessionPicker.screen.tsx\nHistory: SessionHistory.screen.tsx\nUtilities: common/lib/utils.ts (date format)\nHooks: availability/time slots loading\nPicker Flow\nLoad month availability on mount/month change\nDay press → fetch daily slots (debounced; no duplicates)\nToggle shared vs assigned:\nPreserve selectedDate\nIf day has no slots, fallback to previously valid date\nHistory Flow\nTabs: All/Reserved/Completed/Canceled\nFilter with memoized list\nOn focus: reset active tab to All (undefined)\nEmpty states:\nAll empty → show renderPreSessionBtn()\nOthers empty → “ するセッションはありません ”\nRefreshControl.refreshing ← loading\nEdge Cases\nRemove useEffect calling onDayPress causing duplicate calls\nSeparate initial load effect from toggle-marking effect\nAvoid circular deps resetting selected date\nAnalytics\nsession_month_availability_viewed\nsession_day_slots_viewed\nsession_booked, session_rescheduled, session_canceled\nsession_history_tab_selected\nQA\nToggle repeatedly (selected date preserved)\nNo-slot fallback correctness\nHistory empty-state behaviors\nRefresh/Loading linkage\nSupport\nOverview\nContact channels, FAQs, prompts, tooltips orchestrations.\nArchitecture\nActions: getSupportData, sendConversationMessages\nSelectors: worker online, active tooltips, FAQs, overlay flags\nFlows: initialize conversation post-profiling; run tooltips in order; resume app triggers re-checks\nAnalytics\nsupport_tooltip_viewed_{name}\nsupport_faq_loaded\nsupport_conversation_resumed\nQA\nTooltip order gating and user interaction persistence\nConversation resumes after background resume\nReferral\nOverview\nCampaigns, share flows, and conversions.\nArchitecture\nCampaign conditions computed in state/effects\nToast abstraction: common/lib/toast.ts → showToast\nFlows\nCreate referral link (with conditions)\nShare via native sheet\nParse conditions and track conversions\nEdge Cases\nAvoid store access in useMemo (move to useEffect or stabilize dependencies)\nReplace ToastAndroid with showToast\nAnalytics\nreferral_share_initiated\nreferral_link_copied\nreferral_conversion\nQA\niOS/Android share consistency\nCampaign rule enforcement\nMoney Transfer\nOverview\nEntry → validation → review → confirm → status.\nValidation\nAmount boundaries; available balance; allowed recipients; compliance\nErrors\nNetwork backoff; compliance messaging; queued/pending states\nAnalytics\ntransfer_initiated, transfer_review_confirmed, transfer_success, transfer_failed,\ntransfer_limit_exceeded\nQA\nBoundary testing\nMid-flow background/foreground\nOffline retry\nInvestment\nOverview\nHome cards, interest modal, investment navigation.\nArchitecture\nHome: CardCarousel + chips in Home.screen.tsx\nActions: getInvestmentDetails\nMapping: GMO_SERVER_ERRORS for maintenance\nAnalytics\ninvestment_card_viewed\ninterest_modal_opened/closed\ninvestment_chip_clicked\nQA\nMaintenance mapping\nLearn paths for closed accounts\nPerformance\nInsurance\nOverview\nPolicies lifecycle and re-apply flows.\nScreens\nInsurance card/CTA\nCanceled/rejected guidance\nAnalytics\ninsurance_policy_viewed\ninsurance_cta_clicked\ninsurance_reapply_started\nQA\nStatus transitions\nAlert correctness\nMoney Habits (Manabu)\nOverview\nContent ingestion (Dato CMS), tagging, monthly report alerts.\nArchitecture\nQueries: dev/prod CMS\nSelectors: content, tags (interest/category/format), milestones\nActions: store content, show monthly reports\nAnalytics\nmanabu_content_loaded\nmanabu_filters_applied\nmanabu_report_shown\nQA\nFiltering accuracy\nReport eligibility logic\nDeep-link routing to alert screen\nApp Architecture\nNavigation\nRoot container: AppNavigation.tsx (lazy-load via React.Suspense)\nStacks & listeners: AppRoutes.tsx\nHeavy-event deferral via InteractionManager\nState & Side Effects\nRedux modules per domain\nLocal hooks for UI-only state\nDebounce and memoization to reduce re-renders\nNetwork\nGraphQL hooks for CMS\nAndroid background timers via helpers in utils\nAnalytics & Events\nNaming Conventions\n{domain}{action}{outcome} e.g., session_booked_success\nDimensions: platform, app_version, user_id (if allowed), locale\nSources\nAdjust init/config\nOneSignal handlers\nCustom trackers: common/lib/dataTrackers.ts\nQA\nValidate payloads in sandbox\nVolume sanity during high-frequency events\nPermissions & Privacy\nPermissions\nNotifications: prompt + OneSignal subscription check\niOS ATT prompt on suitable moment in onboarding\nResume checks in foreground hook\nPrivacy\nMinimize PII in events\nRespect user settings and gating\nSecure storage for secrets\nNotifications & Deep Links\nOneSignal\nforegroundWillDisplay: intercept and optionally customize\nclick: parse launchURL, dispatch to navigation (defer until foreground checks)\nDeep Links\nRoutes: Home, Consent Refresh, Interest Modal, Chat Thread\nDeferral: wait until auth lock resolved\nQA\nRoute matrix coverage\nLocked/unlocked entry paths\nRelease Process & QA\nCodePush/Updates\nRuntime check: ACTIONS.CHECK_UPDATES_N_RESUME_APP\nAvoid blocking UI on resume; defer heavy handlers\nQA Suites\nPer-domain checklists (this doc)\nPerformance: monitor ANRs and long main-thread tasks\n",
  "url": "",
  "space_key": "",
  "page_id": "",
  "created_date": "2025-09-15",
  "updated_date": "",
  "author": "",
  "labels": [],
  "parent_page": "",
  "extracted_text": "Habitto Mobile – Product & Engineering\nPurpose\nEnd-to-end documentation for product flows, architecture, and QA across Authentication, Onboarding, Chat,\nSession Booking, Support, Referral, Money Transfer, Investment, Insurance, and Money Habits (Manabu).\nTable of Contents\nAuthentication\nOnboarding\nChat (Twilio)\nSession Booking\nSupport\nReferral\nMoney Transfer\nInvestment\nInsurance\nMoney Habits (Manabu)\nApp Architecture\nAnalytics & Events\nPermissions & Privacy\nNotifications & Deep Links\nRelease Process & QA\nConventions\nFile paths in backticks (e.g., src/screens/...)\nEvents snake_case by domain (e.g., auth_biometric_success)\nUse InteractionManager.runAfterInteractions to defer heavy work\nAuthentication\nOverview\nSecure access; foreground lock; biometrics; lifecycle management.\nArchitecture\nHooks: src/screens/Auth/AppLock/useForegroundApplockHook.tsx\nBiometrics UI: src/screens/Common/Biometrics.tsx\nActions: common/actions/appLock.actions.ts, common/actions/common.actions.ts,\ncommon/actions/auth.actions.ts\nReducers: common/reducers/appState.reducer.ts, common/reducers/auth.reducer.ts\nSelectors: common/selectors/appLockSelector.selector.tsx,\ncommon/selectors/authSelectors.selector.tsx\nUtilities: common/lib/DateHandler.ts, common/lib/utils.ts (delay, runInBackground)\nScreens\nBiometric prompt (native) and App Lock gate\nError states: unavailable sensor, opt-out\nFlows\nFirst-time biometric:\nDetect device → prompt → store preference → continue.\nResume from background:\nIf lastActive ≥ 1h and user authenticated: lock → biometric prompt → resume.\nElse: resume silently and run updates (ACTIONS.CHECK_UPDATES_N_RESUME_APP).\nFallback: if biometric disabled/unavailable → passcode or bypass per policy.\nLifecycle & State\nForeground hook:\nOn Active: setFromBackground(true) → setForegroundCheckStatus(true) →\nbiometric if needed → setForegroundCheckStatus(false) → resume tasks.\nOn Background: SET_LAST_ACTIVE_TIME_STAMP, setFromBackground(false).\nEdge Cases\nNotification deep-link while locked → defer until unlocked.\nRapid background/foreground flaps → deduplicate prompts.\nANR mitigation: defer heavy work using InteractionManager.\nAnalytics\nauth_biometric_prompt_shown, auth_biometric_success, auth_biometric_failure, auth_lock_shown,\nauth_resume_completed\nDevices with FaceID/TouchID/None\nResume at <1h and ≥1h\nDeep-links while locked\nAirplane-mode resume\nOnboarding\nOverview\nPermissions, KYC/GMO consent, initial feature gating, tooltips.\nArchitecture\nScreen: src/screens/Dashboard/Home/Home.screen.tsx\nActions: support.actions.ts (e.g., getAccountOpeningStatus,\ngetGMOconsentAgreement), common.actions.ts\nSelectors: accountOpeningStatusSelector, localeSelector\nModals: components/PermissionRequestModal.component.tsx\nDeep-links: root handlers in AppNavigation.tsx\nSteps\nPermissions: notifications (and iOS ATT)\nAccount opening:\nFORM_NOT_SUBMITTED → start application\nPROBLEM_IN_DATA → re-apply\nWITHDRAWN/REJECTED → alternate CTAs\nACCOUNT_ACTIVATED & funded → dashboard\nConsent: open URL, return via deep link.\nInitial setting card if activated but not funded.\nTooltips sequence (savings → insurance → investment → more).\nDeep Links\nWeekly yield modal\nConsent refresh link (refresh helpers → clear deep link)\nEdge Cases\nForeground checks can block initial deep-link handling; defer.\nAvoid duplicate API races; debounce where needed.\nAnalytics\nonboarding_permission_prompt_shown/accepted\nonboarding_kyc_status_updated\nonboarding_initial_setting_action\niOS/Android first-run permutations\nKYC return flows\nPermission toggles mid-flow\nChat (Twilio)\nOverview\nReal-time messaging with text/media; typing; read index; push deep-links.\nArchitecture\nEvents: src/navigation/AppRoutes.tsx (listeners, deferrals)\nUI: react-native-chat-ui/src/components/*\nState: messages, typing, last read index\nModels\nMessage: sid, author, body, timestamp, type (text/image/video/audio/file), attributes, status\n(sending/sent/failed)\nTyping: author → boolean\nRead index: per thread\nEvents\nonMessagesLoad(messages):\nDefer heavy init; set message list; set read index\nmessageAdded(message):\nToggle typing false; increment read index; for media, resolve temp URLs; dispatch updates\nmessageUpdated/Removed:\nUpdate local store accordingly\nInput (Android specifics)\nHeight 40–100 using onContentSizeChange\ntextAlignVertical: 'top'; scrollEnabled when keyboard visible\nHide attachment/AI row when keyboard visible; animate height/opacity\nWhen keyboard hidden, show truncated overlay (ellipsizeMode=\"head\") with the inputʼs text hidden\n(transparent color) to avoid value mutation issues.\nPerformance\nInteractionManager.runAfterInteractions for heavy events\nDebounced dispatches; clean up listeners\nLazy load with React.Suspense and fallback\nAnalytics\nchat_thread_opened/closed\nchat_message_sent/received\nchat_media_sent_{type}\nchat_typing_started/stopped\nchat_push_deeplink_opened\nHigh-volume inbound messages\nAll attachment types\nPush deep-link → thread while app locked/unlocked\nAndroid keyboard: growth/shrink and accessory row behavior\nSession Booking\nOverview\nBook/reschedule advisor sessions; history with status tabs.\nArchitecture\nPicker: CreateSession/SessionPicker.screen.tsx\nHistory: SessionHistory.screen.tsx\nUtilities: common/lib/utils.ts (date format)\nHooks: availability/time slots loading\nPicker Flow\nLoad month availability on mount/month change\nDay press → fetch daily slots (debounced; no duplicates)\nToggle shared vs assigned:\nPreserve selectedDate\nIf day has no slots, fallback to previously valid date\nHistory Flow\nTabs: All/Reserved/Completed/Canceled\nFilter with memoized list\nOn focus: reset active tab to All (undefined)\nEmpty states:\nAll empty → show renderPreSessionBtn()\nOthers empty → “ するセッションはありません ”\nRefreshControl.refreshing ← loading\nEdge Cases\nRemove useEffect calling onDayPress causing duplicate calls\nSeparate initial load effect from toggle-marking effect\nAvoid circular deps resetting selected date\nAnalytics\nsession_month_availability_viewed\nsession_day_slots_viewed\nsession_booked, session_rescheduled, session_canceled\nsession_history_tab_selected\nToggle repeatedly (selected date preserved)\nNo-slot fallback correctness\nHistory empty-state behaviors\nRefresh/Loading linkage\nSupport\nOverview\nContact channels, FAQs, prompts, tooltips orchestrations.\nArchitecture\nActions: getSupportData, sendConversationMessages\nSelectors: worker online, active tooltips, FAQs, overlay flags\nFlows: initialize conversation post-profiling; run tooltips in order; resume app triggers re-checks\nAnalytics\nsupport_tooltip_viewed_{name}\nsupport_faq_loaded\nsupport_conversation_resumed\nTooltip order gating and user interaction persistence\nConversation resumes after background resume\nReferral\nOverview\nCampaigns, share flows, and conversions.\nArchitecture\nCampaign conditions computed in state/effects\nToast abstraction: common/lib/toast.ts → showToast\nFlows\nCreate referral link (with conditions)\nShare via native sheet\nParse conditions and track conversions\nEdge Cases\nAvoid store access in useMemo (move to useEffect or stabilize dependencies)\nReplace ToastAndroid with showToast\nAnalytics\nreferral_share_initiated\nreferral_link_copied\nreferral_conversion\niOS/Android share consistency\nCampaign rule enforcement\nMoney Transfer\nOverview\nEntry → validation → review → confirm → status.\nValidation\nAmount boundaries; available balance; allowed recipients; compliance\nErrors\nNetwork backoff; compliance messaging; queued/pending states\nAnalytics\ntransfer_initiated, transfer_review_confirmed, transfer_success, transfer_failed,\ntransfer_limit_exceeded\nBoundary testing\nMid-flow background/foreground\nOffline retry\nInvestment\nOverview\nHome cards, interest modal, investment navigation.\nArchitecture\nHome: CardCarousel + chips in Home.screen.tsx\nActions: getInvestmentDetails\nMapping: GMO_SERVER_ERRORS for maintenance\nAnalytics\ninvestment_card_viewed\ninterest_modal_opened/closed\ninvestment_chip_clicked\nMaintenance mapping\nLearn paths for closed accounts\nPerformance\nInsurance\nOverview\nPolicies lifecycle and re-apply flows.\nScreens\nInsurance card/CTA\nCanceled/rejected guidance\nAnalytics\ninsurance_policy_viewed\ninsurance_cta_clicked\ninsurance_reapply_started\nStatus transitions\nAlert correctness\nMoney Habits (Manabu)\nOverview\nContent ingestion (Dato CMS), tagging, monthly report alerts.\nArchitecture\nQueries: dev/prod CMS\nSelectors: content, tags (interest/category/format), milestones\nActions: store content, show monthly reports\nAnalytics\nmanabu_content_loaded\nmanabu_filters_applied\nmanabu_report_shown\nFiltering accuracy\nReport eligibility logic\nDeep-link routing to alert screen\nApp Architecture\nNavigation\nRoot container: AppNavigation.tsx (lazy-load via React.Suspense)\nStacks & listeners: AppRoutes.tsx\nHeavy-event deferral via InteractionManager\nState & Side Effects\nRedux modules per domain\nLocal hooks for UI-only state\nDebounce and memoization to reduce re-renders\nNetwork\nGraphQL hooks for CMS\nAndroid background timers via helpers in utils\nAnalytics & Events\nNaming Conventions\n{domain}{action}{outcome} e.g., session_booked_success\nDimensions: platform, app_version, user_id (if allowed), locale\nSources\nAdjust init/config\nOneSignal handlers\nCustom trackers: common/lib/dataTrackers.ts\nValidate payloads in sandbox\nVolume sanity during high-frequency events\nPermissions & Privacy\nPermissions\nNotifications: prompt + OneSignal subscription check\niOS ATT prompt on suitable moment in onboarding\nResume checks in foreground hook\nPrivacy\nMinimize PII in events\nRespect user settings and gating\nSecure storage for secrets\nNotifications & Deep Links\nOneSignal\nforegroundWillDisplay: intercept and optionally customize\nclick: parse launchURL, dispatch to navigation (defer until foreground checks)\nDeep Links\nRoutes: Home, Consent Refresh, Interest Modal, Chat Thread\nDeferral: wait until auth lock resolved\nRoute matrix coverage\nLocked/unlocked entry paths\nRelease Process & QA\nCodePush/Updates\nRuntime check: ACTIONS.CHECK_UPDATES_N_RESUME_APP\nAvoid blocking UI on resume; defer heavy handlers\nQA Suites\nPer-domain checklists (this doc)\nPerformance: monitor ANRs and long main-thread tasks",
  "headings": [
    "First-time biometric",
    "Resume from background",
    "Foreground hook",
    "QA",
    "Account opening",
    "QA",
    "onMessagesLoad(messages)",
    "messageAdded(message)",
    "messageUpdated/Removed",
    "QA",
    "Toggle shared vs assigned",
    "Empty states",
    "QA",
    "QA",
    "QA",
    "QA",
    "QA",
    "QA",
    "QA",
    "QA"
  ],
  "code_blocks": [],
  "links": [],
  "images": [],
  "tables": [],
  "tech_stack_mentions": [
    "React",
    "React",
    "React",
    "Redux",
    "iOS",
    "iOS",
    "iOS",
    "iOS",
    "Android",
    "Android",
    "Android",
    "Android",
    "Android",
    "GraphQL",
    "CodePush",
    "Analytics",
    "Analytics",
    "Analytics",
    "Analytics",
    "Analytics",
    "Analytics",
    "Analytics",
    "Analytics",
    "Analytics",
    "Analytics",
    "Analytics",
    "Analytics",
    "Investment",
    "Investment",
    "Investment",
    "Investment",
    "Investment",
    "Advisor",
    "KYC",
    "KYC",
    "Compliance",
    "Compliance",
    "Dashboard",
    "Dashboard",
    "Analytics",
    "Analytics",
    "Analytics",
    "Analytics",
    "Analytics",
    "Analytics",
    "Analytics",
    "Analytics",
    "Analytics",
    "Analytics",
    "Analytics",
    "Analytics",
    "Notifications",
    "Notifications",
    "Notifications",
    "Notifications",
    "Authentication",
    "Authentication",
    "Authentication",
    "Settings",
    "Filter",
    "Biometric",
    "Biometric",
    "Biometric",
    "Biometric",
    "Biometric",
    "Secure Storage"
  ],
  "api_endpoints": [],
  "component_names": [
    "useForegroundApplockHook",
    "Create",
    "Main",
    "Foreground",
    "useEffect",
    "Account",
    "Advisor",
    "Notification",
    "Update",
    "PermissionRequestModal",
    "Compliance",
    "InteractionManager",
    "Resume",
    "Investment",
    "Dashboard",
    "Toggle",
    "First-time",
    "Empty",
    "DateHandler",
    "SessionPicker",
    "Home",
    "Remove",
    "Auth",
    "Authentication",
    "Settings",
    "Report",
    "useMemo",
    "Filter",
    "Kyc"
  ],
  "feature_descriptions": [
    "Habitto Mobile – Product & Engineering Purpose End-to-end documentation for product flows, architecture, and QA across Authentication, Onboarding, Chat, Session Booking, Support, Referral, Money Transfer, Investment, Insurance, and Money Habits (Manabu)",
    "Table of Contents Authentication Onboarding Chat (Twilio) Session Booking Support Referral Money Transfer Investment Insurance Money Habits (Manabu) App Architecture Analytics & Events Permissions & Privacy Notifications & Deep Links Release Process & QA Conventions File paths in backticks (e",
    "runAfterInteractions to defer heavy work Authentication Overview Secure access; foreground lock; biometrics; lifecycle management",
    "ts (delay, runInBackground) Screens Biometric prompt (native) and App Lock gate Error states: unavailable sensor, opt-out Flows First-time biometric: Detect device → prompt → store preference → continue",
    "ts Selectors: accountOpeningStatusSelector, localeSelector Modals: components/PermissionRequestModal",
    "Tooltips sequence (savings → insurance → investment → more)",
    "Analytics onboarding_permission_prompt_shown/accepted onboarding_kyc_status_updated onboarding_initial_setting_action iOS/Android first-run permutations KYC return flows Permission toggles mid-flow Chat (Twilio) Overview Real-time messaging with text/media; typing; read index; push deep-links",
    "tsx Actions: getInvestmentDetails Mapping: GMO_SERVER_ERRORS for maintenance Analytics investment_card_viewed interest_modal_opened/closed investment_chip_clicked Maintenance mapping Learn paths for closed accounts Performance Insurance Overview Policies lifecycle and re-apply flows",
    "First-time biometric",
    "Resume from background",
    "Foreground hook",
    "Account opening",
    "onMessagesLoad(messages)",
    "messageAdded(message)",
    "messageUpdated/Removed",
    "Toggle shared vs assigned",
    "Empty states"
  ],
  "business_rules": [
    "only state\nDebounce and memoization to reduce re-renders\nNetwork\nGraphQL hooks for CMS\nAndroid background timers via helpers in utils\nAnalytics & Events\nNaming Conventions\n{domain}{action}{outcome} e."
  ],
  "processing_date": "2025-09-15T12:00:26.621558",
  "word_count": 1072,
  "relevance_score": 100.0
}